game_overlay_sdk/__init__.py
game_overlay_sdk/injector.py
game_overlay_sdk/lib/DLLInjection32.dll
game_overlay_sdk/lib/DLLInjection64.dll
game_overlay_sdk/lib/GameOverlay32.dll
game_overlay_sdk/lib/GameOverlay64.dll
game_overlay_sdk/lib/VK_LAYER_OCAT_overlay32.dll
game_overlay_sdk/lib/VK_LAYER_OCAT_overlay32.json
game_overlay_sdk/lib/VK_LAYER_OCAT_overlay64.dll
game_overlay_sdk/lib/VK_LAYER_OCAT_overlay64.json
game_overlay_sdk/lib/comp.spv
game_overlay_sdk/lib/frag.spv
game_overlay_sdk/lib/shader.comp
game_overlay_sdk/lib/shader.frag
game_overlay_sdk/lib/shader.vert
game_overlay_sdk/lib/vert.spv
game_overlay_sdk-1.0.1.dist-info/METADATA
game_overlay_sdk-1.0.1.dist-info/WHEEL
game_overlay_sdk-1.0.1.dist-info/top_level.txt
game_overlay_sdk-1.0.1.dist-info/zip-safe
game_overlay_sdk-1.0.1.dist-info/RECORD
